llama_index/embeddings/oci_genai/__init__.py
llama_index/embeddings/oci_genai/base.py
llama_index_embeddings_oci_genai-0.4.1.dist-info/METADATA
llama_index_embeddings_oci_genai-0.4.1.dist-info/WHEEL
llama_index_embeddings_oci_genai-0.4.1.dist-info/licenses/LICENSE
llama_index_embeddings_oci_genai-0.4.1.dist-info/RECORD
