Metadata-Version: 2.4
Name: llama-index-embeddings-oci-genai
Version: 0.4.1
Summary: llama-index embeddings oci-genai integration
Author-email: Arthur Cheng <arthur.cheng@oracle.com>, Rave Harpaz <rave.harpaz@oracle.com>
License-Expression: MIT
License-File: LICENSE
Requires-Python: <4.0,>=3.9
Requires-Dist: llama-index-core<0.15,>=0.13.0
Requires-Dist: oci>=2.125.3
